backup_reporter/__init__.py
backup_reporter/collector.py
backup_reporter/dataclass.py
backup_reporter/main.py
backup_reporter/reporters.py
backup_reporter/utils.py
backup_reporter-0.5.4.dist-info/LICENSE
backup_reporter-0.5.4.dist-info/METADATA
backup_reporter-0.5.4.dist-info/WHEEL
backup_reporter-0.5.4.dist-info/entry_points.txt
backup_reporter-0.5.4.dist-info/RECORD
