Metadata-Version: 2.1
Name: backup-reporter
Version: 0.5.4
Summary: Collect and show info about various backups
Author: Dmitry Razin
Author-email: d.razin@oom.ag
Requires-Python: >=3.8,<4.0
Classifier: Programming Language :: Python :: 3
Classifier: Programming Language :: Python :: 3.8
Classifier: Programming Language :: Python :: 3.9
Classifier: Programming Language :: Python :: 3.10
Classifier: Programming Language :: Python :: 3.11
Classifier: Programming Language :: Python :: 3.12
Requires-Dist: boto3 (==1.24.27)
Requires-Dist: dateparser (==1.2.0)
Requires-Dist: gspread (==5.0.0)
Requires-Dist: gspread_formatting (==1.2.0)
Requires-Dist: mergedeep (==1.3.4)
Requires-Dist: oauth2client (>=4.1.3,<5.0.0)
Requires-Dist: pytz (==2024.1)
Requires-Dist: pyyaml (==5.1)
